pygraphs/__init__.py
pygraphs/pygraphs_base.py
pygraphs/tools.py
pygraphs-0.0.1.dist-info/LICENSE
pygraphs-0.0.1.dist-info/METADATA
pygraphs-0.0.1.dist-info/WHEEL
pygraphs-0.0.1.dist-info/top_level.txt
pygraphs-0.0.1.dist-info/RECORD
