Metadata-Version: 2.1
Name: pygraphs
Version: 0.0.1
Summary: A graph database based on Python
Home-page: https://github.com/guofei9987/pygraphs
Author: Guo Fei
Author-email: guofei9987@foxmail.com
License: MIT
Platform: linux
Platform: windows
Platform: macos
Requires-Python: >=3.5
